[{"id":749,"graphic":"GEN8- Tar Shot","frames":[[{"x":0,"y":0,"zoomX":100,"zoomY":100,"visible":true,"target":0,"graphicFrame":0,"opacity":255,"locked":true,"priority":1,"focus":3},{"x":128,"y":-64,"zoomX":100,"zoomY":100,"visible":true,"target":1,"graphicFrame":0,"opacity":255,"locked":true,"priority":1,"focus":3},{"x":34.5,"y":-32,"zoomX":112,"zoomY":112,"visible":true,"target":2,"graphicFrame":0,"opacity":84,"priority":1,"focus":3}],[{"x":0,"y":0,"zoomX":100,"zoomY":100,"visible":true,"target":0,"graphicFrame":0,"opacity":255,"locked":true,"priority":1,"focus":3},{"x":128,"y":-64,"zoomX":100,"zoomY":100,"visible":true,"target":1,"graphicFrame":0,"opacity":255,"locked":true,"priority":1,"focus":3},{"x":45.5,"y":-40.5,"zoomX":125,"zoomY":125,"visible":true,"target":2,"graphicFrame":0,"opacity":108,"priority":1,"focus":3}],[{"x":0,"y":0,"zoomX":100,"zoomY":100,"visible":true,"target":0,"graphicFrame":0,"opacity":255,"locked":true,"priority":1,"focus":3},{"x":128,"y":-64,"zoomX":100,"zoomY":100,"visible":true,"target":1,"graphicFrame":0,"opacity":255,"locked":true,"priority":1,"focus":3},{"x":56.5,"y":-49,"zoomX":137,"zoomY":137,"visible":true,"target":2,"graphicFrame":0,"opacity":133,"priority":1,"focus":3}],[{"x":0,"y":0,"zoomX":100,"zoomY":100,"visible":true,"target":0,"graphicFrame":0,"opacity":255,"locked":true,"priority":1,"focus":3},{"x":128,"y":-64,"zoomX":100,"zoomY":100,"visible":true,"target":1,"graphicFrame":0,"opacity":255,"locked":true,"priority":1,"focus":3},{"x":68,"y":-57.5,"zoomX":150,"zoomY":150,"visible":true,"target":2,"graphicFrame":0,"opacity":157,"priority":1,"focus":3}],[{"x":0,"y":0,"zoomX":100,"zoomY":100,"visible":true,"target":0,"graphicFrame":0,"opacity":255,"locked":true,"priority":1,"focus":3},{"x":128,"y":-64,"zoomX":100,"zoomY":100,"visible":true,"target":1,"graphicFrame":0,"opacity":255,"locked":true,"priority":1,"focus":3},{"x":79,"y":-66,"zoomX":162,"zoomY":162,"visible":true,"target":2,"graphicFrame":0,"opacity":181,"priority":1,"focus":3}],[{"x":0,"y":0,"zoomX":100,"zoomY":100,"visible":true,"target":0,"graphicFrame":0,"opacity":255,"locked":true,"priority":1,"focus":3},{"x":128,"y":-64,"zoomX":100,"zoomY":100,"visible":true,"target":1,"graphicFrame":0,"opacity":255,"locked":true,"priority":1,"focus":3},{"x":90,"y":-74.5,"zoomX":175,"zoomY":175,"visible":true,"target":2,"graphicFrame":0,"opacity":206,"priority":1,"focus":3}],[{"x":0,"y":0,"zoomX":100,"zoomY":100,"visible":true,"target":0,"graphicFrame":0,"opacity":255,"locked":true,"priority":1,"focus":3},{"x":128,"y":-64,"zoomX":100,"zoomY":100,"visible":true,"target":1,"graphicFrame":0,"opacity":255,"locked":true,"priority":1,"focus":3},{"x":101,"y":-79,"zoomX":187,"zoomY":187,"visible":true,"target":2,"graphicFrame":0,"opacity":230,"priority":1,"focus":3}],[{"x":0,"y":0,"zoomX":100,"zoomY":100,"visible":true,"target":0,"graphicFrame":0,"opacity":255,"locked":true,"priority":1,"focus":3},{"x":128,"y":-64,"zoomX":100,"zoomY":100,"visible":true,"target":1,"graphicFrame":0,"opacity":255,"locked":true,"priority":1,"focus":3},{"x":112.5,"y":-83.5,"zoomX":200,"zoomY":200,"visible":true,"target":2,"graphicFrame":0,"opacity":255,"priority":1,"focus":3}],[{"x":0,"y":0,"zoomX":100,"zoomY":100,"visible":true,"target":0,"graphicFrame":0,"opacity":255,"locked":true,"priority":1,"focus":3},{"x":128,"y":-64,"zoomX":100,"zoomY":100,"visible":true,"target":1,"graphicFrame":0,"opacity":255,"locked":true,"priority":1,"focus":3},{"x":116,"y":-83.5,"zoomX":200,"zoomY":200,"visible":true,"target":2,"graphicFrame":0,"opacity":255,"priority":1,"focus":3}],[{"x":0,"y":0,"zoomX":100,"zoomY":100,"visible":true,"target":0,"graphicFrame":0,"opacity":255,"locked":true,"priority":1,"focus":3},{"x":128,"y":-64,"zoomX":100,"zoomY":100,"visible":true,"target":1,"graphicFrame":0,"opacity":255,"locked":true,"priority":1,"focus":3},{"x":125,"y":-78,"zoomX":100,"zoomY":100,"visible":true,"target":2,"graphicFrame":2,"opacity":110,"priority":1,"focus":3},{"x":120,"y":-83.5,"zoomX":200,"zoomY":200,"visible":true,"target":2,"graphicFrame":0,"opacity":170,"priority":1,"focus":3}],[{"x":0,"y":0,"zoomX":100,"zoomY":100,"visible":true,"target":0,"graphicFrame":0,"opacity":255,"locked":true,"priority":1,"focus":3},{"x":128,"y":-64,"zoomX":100,"zoomY":100,"visible":true,"target":1,"graphicFrame":0,"opacity":255,"locked":true,"priority":1,"focus":3},{"x":125,"y":-78.5,"zoomX":100,"zoomY":100,"visible":true,"target":2,"graphicFrame":1,"opacity":140,"priority":1,"focus":1}],[{"x":0,"y":0,"zoomX":100,"zoomY":100,"visible":true,"target":0,"graphicFrame":0,"opacity":255,"locked":true,"priority":1,"focus":3},{"x":128,"y":-64,"zoomX":100,"zoomY":100,"visible":true,"target":1,"graphicFrame":0,"opacity":255,"locked":true,"priority":1,"focus":3},{"x":125,"y":-78.5,"zoomX":100,"zoomY":100,"visible":true,"target":2,"graphicFrame":1,"opacity":170,"priority":1,"focus":1}],[{"x":0,"y":0,"zoomX":100,"zoomY":100,"visible":true,"target":0,"graphicFrame":0,"opacity":255,"locked":true,"priority":1,"focus":3},{"x":128,"y":-64,"zoomX":100,"zoomY":100,"visible":true,"target":1,"graphicFrame":0,"opacity":255,"locked":true,"priority":1,"focus":3},{"x":125,"y":-78.5,"zoomX":100,"zoomY":100,"visible":true,"target":2,"graphicFrame":1,"opacity":255,"priority":1,"focus":1},{"x":90.5,"y":-56.5,"zoomX":100,"zoomY":100,"visible":true,"target":2,"graphicFrame":1,"opacity":140,"priority":1,"focus":1}],[{"x":0,"y":0,"zoomX":100,"zoomY":100,"visible":true,"target":0,"graphicFrame":0,"opacity":255,"locked":true,"priority":1,"focus":3},{"x":128,"y":-64,"zoomX":100,"zoomY":100,"visible":true,"target":1,"graphicFrame":0,"opacity":255,"locked":true,"priority":1,"focus":3},{"x":125,"y":-78.5,"zoomX":100,"zoomY":100,"visible":true,"target":2,"graphicFrame":1,"opacity":255,"priority":1,"focus":1},{"x":90.5,"y":-56.5,"zoomX":100,"zoomY":100,"visible":true,"target":2,"graphicFrame":1,"opacity":140,"priority":1,"focus":1}],[{"x":0,"y":0,"zoomX":100,"zoomY":100,"visible":true,"target":0,"graphicFrame":0,"opacity":255,"locked":true,"priority":1,"focus":3},{"x":128,"y":-64,"zoomX":100,"zoomY":100,"visible":true,"target":1,"graphicFrame":0,"opacity":255,"locked":true,"priority":1,"focus":3},{"x":125,"y":-78.5,"zoomX":100,"zoomY":100,"visible":true,"target":2,"graphicFrame":1,"opacity":255,"priority":1,"focus":1},{"x":90.5,"y":-56.5,"zoomX":100,"zoomY":100,"visible":true,"target":2,"graphicFrame":1,"opacity":170,"priority":1,"focus":1}],[{"x":0,"y":0,"zoomX":100,"zoomY":100,"visible":true,"target":0,"graphicFrame":0,"opacity":255,"locked":true,"priority":1,"focus":3},{"x":128,"y":-64,"zoomX":100,"zoomY":100,"visible":true,"target":1,"graphicFrame":0,"opacity":255,"locked":true,"priority":1,"focus":3},{"x":125,"y":-78.5,"zoomX":100,"zoomY":100,"visible":true,"target":2,"graphicFrame":1,"opacity":255,"priority":1,"focus":1},{"x":90.5,"y":-56.5,"zoomX":100,"zoomY":100,"visible":true,"target":2,"graphicFrame":1,"opacity":170,"priority":1,"focus":1}],[{"x":0,"y":0,"zoomX":100,"zoomY":100,"visible":true,"target":0,"graphicFrame":0,"opacity":255,"locked":true,"priority":1,"focus":3},{"x":128,"y":-64,"zoomX":100,"zoomY":100,"visible":true,"target":1,"graphicFrame":0,"opacity":255,"locked":true,"priority":1,"focus":3},{"x":125,"y":-78.5,"zoomX":100,"zoomY":100,"visible":true,"target":2,"graphicFrame":1,"opacity":255,"priority":1,"focus":1},{"x":90.5,"y":-56.5,"zoomX":100,"zoomY":100,"visible":true,"target":2,"graphicFrame":1,"opacity":255,"priority":1,"focus":1},{"x":162,"y":-56.5,"zoomX":100,"zoomY":100,"visible":true,"target":2,"graphicFrame":1,"opacity":140,"priority":1,"focus":1}],[{"x":0,"y":0,"zoomX":100,"zoomY":100,"visible":true,"target":0,"graphicFrame":0,"opacity":255,"locked":true,"priority":1,"focus":3},{"x":128,"y":-64,"zoomX":100,"zoomY":100,"visible":true,"target":1,"graphicFrame":0,"opacity":255,"locked":true,"priority":1,"focus":3},{"x":125,"y":-78.5,"zoomX":100,"zoomY":100,"visible":true,"target":2,"graphicFrame":1,"opacity":255,"priority":1,"focus":1},{"x":90.5,"y":-56.5,"zoomX":100,"zoomY":100,"visible":true,"target":2,"graphicFrame":1,"opacity":255,"priority":1,"focus":1},{"x":162,"y":-56.5,"zoomX":100,"zoomY":100,"visible":true,"target":2,"graphicFrame":1,"opacity":140,"priority":1,"focus":1}],[{"x":0,"y":0,"zoomX":100,"zoomY":100,"visible":true,"target":0,"graphicFrame":0,"opacity":255,"locked":true,"priority":1,"focus":3},{"x":128,"y":-64,"zoomX":100,"zoomY":100,"visible":true,"target":1,"graphicFrame":0,"opacity":255,"locked":true,"priority":1,"focus":3},{"x":125,"y":-78.5,"zoomX":100,"zoomY":100,"visible":true,"target":2,"graphicFrame":1,"opacity":255,"priority":1,"focus":1},{"x":90.5,"y":-56.5,"zoomX":100,"zoomY":100,"visible":true,"target":2,"graphicFrame":1,"opacity":255,"priority":1,"focus":1},{"x":162,"y":-56.5,"zoomX":100,"zoomY":100,"visible":true,"target":2,"graphicFrame":1,"opacity":170,"priority":1,"focus":1}],[{"x":0,"y":0,"zoomX":100,"zoomY":100,"visible":true,"target":0,"graphicFrame":0,"opacity":255,"locked":true,"priority":1,"focus":3},{"x":128,"y":-64,"zoomX":100,"zoomY":100,"visible":true,"target":1,"graphicFrame":0,"opacity":255,"locked":true,"priority":1,"focus":3},{"x":125,"y":-78.5,"zoomX":100,"zoomY":100,"visible":true,"target":2,"graphicFrame":1,"opacity":255,"priority":1,"focus":1},{"x":90.5,"y":-56.5,"zoomX":100,"zoomY":100,"visible":true,"target":2,"graphicFrame":1,"opacity":255,"priority":1,"focus":1},{"x":162,"y":-56.5,"zoomX":100,"zoomY":100,"visible":true,"target":2,"graphicFrame":1,"opacity":255,"priority":1,"focus":1}],[{"x":0,"y":0,"zoomX":100,"zoomY":100,"visible":true,"target":0,"graphicFrame":0,"opacity":255,"locked":true,"priority":1,"focus":3},{"x":128,"y":-64,"zoomX":100,"zoomY":100,"visible":true,"target":1,"graphicFrame":0,"opacity":255,"locked":true,"priority":1,"focus":3}],[{"x":0,"y":0,"zoomX":100,"zoomY":100,"visible":true,"target":0,"graphicFrame":0,"opacity":255,"locked":true,"priority":1,"focus":3},{"x":128,"y":-64,"zoomX":100,"zoomY":100,"visible":true,"target":1,"graphicFrame":0,"opacity":255,"locked":true,"priority":1,"focus":3}],[{"x":0,"y":0,"zoomX":100,"zoomY":100,"visible":true,"target":0,"graphicFrame":0,"opacity":255,"locked":true,"priority":1,"focus":3},{"x":128,"y":-64,"zoomX":100,"zoomY":100,"visible":true,"target":1,"graphicFrame":0,"opacity":255,"locked":true,"priority":1,"focus":3}],[{"x":0,"y":0,"zoomX":100,"zoomY":100,"visible":true,"target":0,"graphicFrame":0,"opacity":255,"locked":true,"priority":1,"focus":3},{"x":128,"y":-64,"zoomX":100,"zoomY":100,"visible":true,"target":1,"graphicFrame":0,"opacity":255,"locked":true,"priority":1,"focus":3}],[{"x":0,"y":0,"zoomX":100,"zoomY":100,"visible":true,"target":0,"graphicFrame":0,"opacity":255,"locked":true,"priority":1,"focus":3},{"x":128,"y":-64,"zoomX":100,"zoomY":100,"visible":true,"target":1,"graphicFrame":0,"opacity":255,"locked":true,"priority":1,"focus":3}],[{"x":0,"y":0,"zoomX":100,"zoomY":100,"visible":true,"target":0,"graphicFrame":0,"opacity":255,"locked":true,"priority":1,"focus":3},{"x":128,"y":-64,"zoomX":100,"zoomY":100,"visible":true,"target":1,"graphicFrame":0,"opacity":255,"locked":true,"priority":1,"focus":3}]],"frameTimedEvents":{"0":[{"frameIndex":0,"resourceName":"PRSFX- Acid Spray.wav","volume":100,"pitch":100,"eventType":"AnimTimedSoundEvent"}]},"position":1,"hue":0},{"id":749,"graphic":"GEN8- Tar Shot","frames":[[{"x":0,"y":0,"zoomX":100,"zoomY":100,"visible":true,"target":0,"graphicFrame":0,"opacity":255,"locked":true,"priority":1,"focus":3},{"x":128,"y":-64,"zoomX":100,"zoomY":100,"visible":true,"target":1,"graphicFrame":0,"opacity":255,"locked":true,"priority":1,"focus":3},{"x":97,"y":-68,"zoomX":111,"zoomY":111,"visible":true,"target":2,"graphicFrame":0,"opacity":117,"priority":1,"focus":3}],[{"x":0,"y":0,"zoomX":100,"zoomY":100,"visible":true,"target":0,"graphicFrame":0,"opacity":255,"locked":true,"priority":1,"focus":3},{"x":128,"y":-64,"zoomX":100,"zoomY":100,"visible":true,"target":1,"graphicFrame":0,"opacity":255,"locked":true,"priority":1,"focus":3},{"x":86,"y":-62,"zoomX":122,"zoomY":122,"visible":true,"target":2,"graphicFrame":0,"opacity":134,"priority":1,"focus":3}],[{"x":0,"y":0,"zoomX":100,"zoomY":100,"visible":true,"target":0,"graphicFrame":0,"opacity":255,"locked":true,"priority":1,"focus":3},{"x":128,"y":-64,"zoomX":100,"zoomY":100,"visible":true,"target":1,"graphicFrame":0,"opacity":255,"locked":true,"priority":1,"focus":3},{"x":75,"y":-56,"zoomX":133,"zoomY":133,"visible":true,"target":2,"graphicFrame":0,"opacity":151,"priority":1,"focus":3}],[{"x":0,"y":0,"zoomX":100,"zoomY":100,"visible":true,"target":0,"graphicFrame":0,"opacity":255,"locked":true,"priority":1,"focus":3},{"x":128,"y":-64,"zoomX":100,"zoomY":100,"visible":true,"target":1,"graphicFrame":0,"opacity":255,"locked":true,"priority":1,"focus":3},{"x":63.5,"y":-50,"zoomX":144,"zoomY":144,"visible":true,"target":2,"graphicFrame":0,"opacity":168,"priority":1,"focus":3}],[{"x":0,"y":0,"zoomX":100,"zoomY":100,"visible":true,"target":0,"graphicFrame":0,"opacity":255,"locked":true,"priority":1,"focus":3},{"x":128,"y":-64,"zoomX":100,"zoomY":100,"visible":true,"target":1,"graphicFrame":0,"opacity":255,"locked":true,"priority":1,"focus":3},{"x":52.5,"y":-44,"zoomX":155,"zoomY":155,"visible":true,"target":2,"graphicFrame":0,"opacity":186,"priority":1,"focus":3}],[{"x":0,"y":0,"zoomX":100,"zoomY":100,"visible":true,"target":0,"graphicFrame":0,"opacity":255,"locked":true,"priority":1,"focus":3},{"x":128,"y":-64,"zoomX":100,"zoomY":100,"visible":true,"target":1,"graphicFrame":0,"opacity":255,"locked":true,"priority":1,"focus":3},{"x":41.5,"y":-38,"zoomX":166,"zoomY":166,"visible":true,"target":2,"graphicFrame":0,"opacity":203,"priority":1,"focus":3}],[{"x":0,"y":0,"zoomX":100,"zoomY":100,"visible":true,"target":0,"graphicFrame":0,"opacity":255,"locked":true,"priority":1,"focus":3},{"x":128,"y":-64,"zoomX":100,"zoomY":100,"visible":true,"target":1,"graphicFrame":0,"opacity":255,"locked":true,"priority":1,"focus":3},{"x":30,"y":-32,"zoomX":177,"zoomY":177,"visible":true,"target":2,"graphicFrame":0,"opacity":220,"priority":1,"focus":3}],[{"x":0,"y":0,"zoomX":100,"zoomY":100,"visible":true,"target":0,"graphicFrame":0,"opacity":255,"locked":true,"priority":1,"focus":3},{"x":128,"y":-64,"zoomX":100,"zoomY":100,"visible":true,"target":1,"graphicFrame":0,"opacity":255,"locked":true,"priority":1,"focus":3},{"x":19,"y":-26,"zoomX":188,"zoomY":188,"visible":true,"target":2,"graphicFrame":0,"opacity":237,"priority":1,"focus":3}],[{"x":0,"y":0,"zoomX":100,"zoomY":100,"visible":true,"target":0,"graphicFrame":0,"opacity":255,"locked":true,"priority":1,"focus":3},{"x":128,"y":-64,"zoomX":100,"zoomY":100,"visible":true,"target":1,"graphicFrame":0,"opacity":255,"locked":true,"priority":1,"focus":3},{"x":8,"y":-19.5,"zoomX":200,"zoomY":200,"visible":true,"target":2,"graphicFrame":0,"opacity":255,"priority":1,"focus":3}],[{"x":0,"y":0,"zoomX":100,"zoomY":100,"visible":true,"target":0,"graphicFrame":0,"opacity":255,"locked":true,"priority":1,"focus":3},{"x":128,"y":-64,"zoomX":100,"zoomY":100,"visible":true,"target":1,"graphicFrame":0,"opacity":255,"locked":true,"priority":1,"focus":3},{"x":-4,"y":-15.5,"zoomX":100,"zoomY":100,"visible":true,"target":2,"graphicFrame":2,"opacity":110,"priority":1,"focus":3},{"x":4,"y":-22.5,"zoomX":100,"zoomY":100,"visible":true,"target":2,"graphicFrame":2,"opacity":110,"priority":1,"focus":3},{"x":9,"y":-12,"zoomX":100,"zoomY":100,"visible":true,"target":2,"graphicFrame":2,"opacity":110,"priority":1,"focus":3},{"x":4,"y":-17.5,"zoomX":200,"zoomY":200,"visible":true,"target":2,"graphicFrame":0,"opacity":170,"priority":1,"focus":3}],[{"x":0,"y":0,"zoomX":100,"zoomY":100,"visible":true,"target":0,"graphicFrame":0,"opacity":255,"locked":true,"priority":1,"focus":3},{"x":128,"y":-64,"zoomX":100,"zoomY":100,"visible":true,"target":1,"graphicFrame":0,"opacity":255,"locked":true,"priority":1,"focus":3},{"x":-4,"y":-11.5,"zoomX":100,"zoomY":100,"visible":true,"target":2,"graphicFrame":2,"opacity":180,"priority":1,"focus":3},{"x":4,"y":-18.5,"zoomX":100,"zoomY":100,"visible":true,"target":2,"graphicFrame":2,"opacity":180,"priority":1,"focus":3},{"x":12,"y":-8,"zoomX":100,"zoomY":100,"visible":true,"target":2,"graphicFrame":2,"opacity":180,"priority":1,"focus":3},{"x":-1.5,"y":-23.5,"zoomX":100,"zoomY":100,"visible":true,"target":2,"graphicFrame":2,"opacity":110,"priority":1,"focus":3},{"x":11.5,"y":-23.5,"zoomX":100,"zoomY":100,"visible":true,"target":2,"graphicFrame":2,"opacity":110,"priority":1,"focus":3},{"x":4,"y":-17.5,"zoomX":200,"zoomY":200,"visible":true,"target":2,"graphicFrame":0,"opacity":100,"priority":1,"focus":3}],[{"x":0,"y":0,"zoomX":100,"zoomY":100,"visible":true,"target":0,"graphicFrame":0,"opacity":255,"locked":true,"priority":1,"focus":3},{"x":128,"y":-64,"zoomX":100,"zoomY":100,"visible":true,"target":1,"graphicFrame":0,"opacity":255,"locked":true,"priority":1,"focus":3},{"x":-8,"y":-7.5,"zoomX":100,"zoomY":100,"visible":true,"target":2,"graphicFrame":2,"opacity":180,"priority":1,"focus":3},{"x":4,"y":-14.5,"zoomX":100,"zoomY":100,"visible":true,"target":2,"graphicFrame":2,"opacity":180,"priority":1,"focus":3},{"x":16,"y":-4,"zoomX":100,"zoomY":100,"visible":true,"target":2,"graphicFrame":2,"opacity":180,"priority":1,"focus":3},{"x":-1.5,"y":-19.5,"zoomX":100,"zoomY":100,"visible":true,"target":2,"graphicFrame":2,"opacity":180,"priority":1,"focus":3},{"x":11.5,"y":-19.5,"zoomX":100,"zoomY":100,"visible":true,"target":2,"graphicFrame":2,"opacity":180,"priority":1,"focus":3},{"x":4,"y":-22,"zoomX":100,"zoomY":100,"visible":true,"target":2,"graphicFrame":2,"opacity":110,"priority":1,"focus":3},{"x":3,"y":-6.5,"zoomX":100,"zoomY":100,"visible":true,"target":2,"graphicFrame":2,"opacity":110,"priority":1,"focus":3}],[{"x":0,"y":0,"zoomX":100,"zoomY":100,"visible":true,"target":0,"graphicFrame":0,"opacity":255,"locked":true,"priority":1,"focus":3},{"x":128,"y":-64,"zoomX":100,"zoomY":100,"visible":true,"target":1,"graphicFrame":0,"opacity":255,"locked":true,"priority":1,"focus":3},{"x":-12,"y":-3.5,"zoomX":100,"zoomY":100,"visible":true,"target":2,"graphicFrame":2,"opacity":180,"priority":1,"focus":3},{"x":0,"y":-10.5,"zoomX":100,"zoomY":100,"visible":true,"target":2,"graphicFrame":2,"opacity":180,"priority":1,"focus":3},{"x":20,"y":0,"zoomX":100,"zoomY":100,"visible":true,"target":2,"graphicFrame":2,"opacity":180,"priority":1,"focus":3},{"x":-8,"y":-15.5,"zoomX":100,"zoomY":100,"visible":true,"target":2,"graphicFrame":2,"opacity":180,"priority":1,"focus":3},{"x":12,"y":-15.5,"zoomX":100,"zoomY":100,"visible":true,"target":2,"graphicFrame":2,"opacity":180,"priority":1,"focus":3},{"x":4,"y":-18,"zoomX":100,"zoomY":100,"visible":true,"target":2,"graphicFrame":2,"opacity":180,"priority":1,"focus":3},{"x":3,"y":-2.5,"zoomX":100,"zoomY":100,"visible":true,"target":2,"graphicFrame":2,"opacity":180,"priority":1,"focus":3}],[{"x":0,"y":0,"zoomX":100,"zoomY":100,"visible":true,"target":0,"graphicFrame":0,"opacity":255,"locked":true,"priority":1,"focus":3},{"x":128,"y":-64,"zoomX":100,"zoomY":100,"visible":true,"target":1,"graphicFrame":0,"opacity":255,"locked":true,"priority":1,"focus":3},{"x":-12,"y":0.5,"zoomX":100,"zoomY":100,"visible":true,"target":2,"graphicFrame":2,"opacity":180,"priority":1,"focus":3},{"x":-4,"y":-6.5,"zoomX":100,"zoomY":100,"visible":true,"target":2,"graphicFrame":2,"opacity":180,"priority":1,"focus":3},{"x":20,"y":4,"zoomX":100,"zoomY":100,"visible":true,"target":2,"graphicFrame":2,"opacity":180,"priority":1,"focus":3},{"x":-8,"y":-11.5,"zoomX":100,"zoomY":100,"visible":true,"target":2,"graphicFrame":2,"opacity":180,"priority":1,"focus":3},{"x":16,"y":-11.5,"zoomX":100,"zoomY":100,"visible":true,"target":2,"graphicFrame":2,"opacity":180,"priority":1,"focus":3},{"x":4,"y":-14,"zoomX":100,"zoomY":100,"visible":true,"target":2,"graphicFrame":2,"opacity":180,"priority":1,"focus":3},{"x":4,"y":1.5,"zoomX":100,"zoomY":100,"visible":true,"target":2,"graphicFrame":2,"opacity":180,"priority":1,"focus":3}],[{"x":0,"y":0,"zoomX":100,"zoomY":100,"visible":true,"target":0,"graphicFrame":0,"opacity":255,"locked":true,"priority":1,"focus":3},{"x":128,"y":-64,"zoomX":100,"zoomY":100,"visible":true,"target":1,"graphicFrame":0,"opacity":255,"locked":true,"priority":1,"focus":3},{"x":-16,"y":4.5,"zoomX":100,"zoomY":100,"visible":true,"target":2,"graphicFrame":2,"opacity":180,"priority":1,"focus":3},{"x":-4,"y":-2.5,"zoomX":100,"zoomY":100,"visible":true,"target":2,"graphicFrame":2,"opacity":180,"priority":1,"focus":3},{"x":24,"y":8,"zoomX":100,"zoomY":100,"visible":true,"target":2,"graphicFrame":2,"opacity":180,"priority":1,"focus":3},{"x":-12,"y":-7.5,"zoomX":100,"zoomY":100,"visible":true,"target":2,"graphicFrame":2,"opacity":180,"priority":1,"focus":3},{"x":20,"y":-7.5,"zoomX":100,"zoomY":100,"visible":true,"target":2,"graphicFrame":2,"opacity":180,"priority":1,"focus":3},{"x":8,"y":-10,"zoomX":100,"zoomY":100,"visible":true,"target":2,"graphicFrame":2,"opacity":180,"priority":1,"focus":3},{"x":4,"y":5.5,"zoomX":100,"zoomY":100,"visible":true,"target":2,"graphicFrame":2,"opacity":180,"priority":1,"focus":3}],[{"x":0,"y":0,"zoomX":100,"zoomY":100,"visible":true,"target":0,"graphicFrame":0,"opacity":255,"locked":true,"priority":1,"focus":3},{"x":128,"y":-64,"zoomX":100,"zoomY":100,"visible":true,"target":1,"graphicFrame":0,"opacity":255,"locked":true,"priority":1,"focus":3},{"x":-16,"y":8.5,"zoomX":100,"zoomY":100,"visible":true,"target":2,"graphicFrame":2,"opacity":180,"priority":1,"focus":3},{"x":-4,"y":1.5,"zoomX":100,"zoomY":100,"visible":true,"target":2,"graphicFrame":2,"opacity":180,"priority":1,"focus":3},{"x":24,"y":12,"zoomX":100,"zoomY":100,"visible":true,"target":2,"graphicFrame":2,"opacity":180,"priority":1,"focus":3},{"x":-12,"y":-3.5,"zoomX":100,"zoomY":100,"visible":true,"target":2,"graphicFrame":2,"opacity":180,"priority":1,"focus":3},{"x":20,"y":-3.5,"zoomX":100,"zoomY":100,"visible":true,"target":2,"graphicFrame":2,"opacity":180,"priority":1,"focus":3},{"x":8,"y":-6,"zoomX":100,"zoomY":100,"visible":true,"target":2,"graphicFrame":2,"opacity":180,"priority":1,"focus":3},{"x":8,"y":9.5,"zoomX":100,"zoomY":100,"visible":true,"target":2,"graphicFrame":2,"opacity":180,"priority":1,"focus":3}],[{"x":0,"y":0,"zoomX":100,"zoomY":100,"visible":true,"target":0,"graphicFrame":0,"opacity":255,"locked":true,"priority":1,"focus":3},{"x":128,"y":-64,"zoomX":100,"zoomY":100,"visible":true,"target":1,"graphicFrame":0,"opacity":255,"locked":true,"priority":1,"focus":3},{"x":-20,"y":12.5,"zoomX":100,"zoomY":100,"visible":true,"target":2,"graphicFrame":2,"opacity":180,"priority":1,"focus":3},{"x":-4,"y":5.5,"zoomX":100,"zoomY":100,"visible":true,"target":2,"graphicFrame":2,"opacity":180,"priority":1,"focus":3},{"x":28,"y":16,"zoomX":100,"zoomY":100,"visible":true,"target":2,"graphicFrame":2,"opacity":180,"priority":1,"focus":3},{"x":-16,"y":0.5,"zoomX":100,"zoomY":100,"visible":true,"target":2,"graphicFrame":2,"opacity":180,"priority":1,"focus":3},{"x":24,"y":0.5,"zoomX":100,"zoomY":100,"visible":true,"target":2,"graphicFrame":2,"opacity":180,"priority":1,"focus":3},{"x":8,"y":-2,"zoomX":100,"zoomY":100,"visible":true,"target":2,"graphicFrame":2,"opacity":180,"priority":1,"focus":3},{"x":8,"y":13.5,"zoomX":100,"zoomY":100,"visible":true,"target":2,"graphicFrame":2,"opacity":180,"priority":1,"focus":3}],[{"x":0,"y":0,"zoomX":100,"zoomY":100,"visible":true,"target":0,"graphicFrame":0,"opacity":255,"locked":true,"priority":1,"focus":3},{"x":128,"y":-64,"zoomX":100,"zoomY":100,"visible":true,"target":1,"graphicFrame":0,"opacity":255,"locked":true,"priority":1,"focus":3},{"x":-24,"y":16.5,"zoomX":100,"zoomY":100,"visible":true,"target":2,"graphicFrame":2,"opacity":180,"priority":1,"focus":3},{"x":-4,"y":9.5,"zoomX":100,"zoomY":100,"visible":true,"target":2,"graphicFrame":2,"opacity":180,"priority":1,"focus":3},{"x":32,"y":20,"zoomX":100,"zoomY":100,"visible":true,"target":2,"graphicFrame":2,"opacity":180,"priority":1,"focus":3},{"x":-16,"y":4.5,"zoomX":100,"zoomY":100,"visible":true,"target":2,"graphicFrame":2,"opacity":180,"priority":1,"focus":3},{"x":24,"y":4.5,"zoomX":100,"zoomY":100,"visible":true,"target":2,"graphicFrame":2,"opacity":180,"priority":1,"focus":3},{"x":12,"y":2,"zoomX":100,"zoomY":100,"visible":true,"target":2,"graphicFrame":2,"opacity":180,"priority":1,"focus":3},{"x":8,"y":17.5,"zoomX":100,"zoomY":100,"visible":true,"target":2,"graphicFrame":2,"opacity":180,"priority":1,"focus":3}],[{"x":0,"y":0,"zoomX":100,"zoomY":100,"visible":true,"target":0,"graphicFrame":0,"opacity":255,"locked":true,"priority":1,"focus":3},{"x":128,"y":-64,"zoomX":100,"zoomY":100,"visible":true,"target":1,"graphicFrame":0,"opacity":255,"locked":true,"priority":1,"focus":3},{"x":-24,"y":20.5,"zoomX":100,"zoomY":100,"visible":true,"target":2,"graphicFrame":2,"opacity":180,"priority":1,"focus":3},{"x":-8,"y":13.5,"zoomX":100,"zoomY":100,"visible":true,"target":2,"graphicFrame":2,"opacity":180,"priority":1,"focus":3},{"x":32,"y":24,"zoomX":100,"zoomY":100,"visible":true,"target":2,"graphicFrame":2,"opacity":180,"priority":1,"focus":3},{"x":-16,"y":8.5,"zoomX":100,"zoomY":100,"visible":true,"target":2,"graphicFrame":2,"opacity":180,"priority":1,"focus":3},{"x":28,"y":8.5,"zoomX":100,"zoomY":100,"visible":true,"target":2,"graphicFrame":2,"opacity":180,"priority":1,"focus":3},{"x":16,"y":6,"zoomX":100,"zoomY":100,"visible":true,"target":2,"graphicFrame":2,"opacity":180,"priority":1,"focus":3},{"x":8,"y":21.5,"zoomX":100,"zoomY":100,"visible":true,"target":2,"graphicFrame":2,"opacity":180,"priority":1,"focus":3}],[{"x":0,"y":0,"zoomX":100,"zoomY":100,"visible":true,"target":0,"graphicFrame":0,"opacity":255,"locked":true,"priority":1,"focus":3},{"x":128,"y":-64,"zoomX":100,"zoomY":100,"visible":true,"target":1,"graphicFrame":0,"opacity":255,"locked":true,"priority":1,"focus":3},{"x":-24,"y":24.5,"zoomX":100,"zoomY":100,"visible":true,"target":2,"graphicFrame":2,"opacity":180,"priority":1,"focus":3},{"x":-8,"y":17.5,"zoomX":100,"zoomY":100,"visible":true,"target":2,"graphicFrame":2,"opacity":180,"priority":1,"focus":3},{"x":32,"y":28,"zoomX":100,"zoomY":100,"visible":true,"target":2,"graphicFrame":2,"opacity":180,"priority":1,"focus":3},{"x":-16,"y":12.5,"zoomX":100,"zoomY":100,"visible":true,"target":2,"graphicFrame":2,"opacity":180,"priority":1,"focus":3},{"x":28,"y":12.5,"zoomX":100,"zoomY":100,"visible":true,"target":2,"graphicFrame":2,"opacity":180,"priority":1,"focus":3},{"x":16,"y":10,"zoomX":100,"zoomY":100,"visible":true,"target":2,"graphicFrame":2,"opacity":180,"priority":1,"focus":3},{"x":8,"y":25.5,"zoomX":100,"zoomY":100,"visible":true,"target":2,"graphicFrame":2,"opacity":180,"priority":1,"focus":3}],[{"x":0,"y":0,"zoomX":100,"zoomY":100,"visible":true,"target":0,"graphicFrame":0,"opacity":255,"locked":true,"priority":1,"focus":3},{"x":128,"y":-64,"zoomX":100,"zoomY":100,"visible":true,"target":1,"graphicFrame":0,"opacity":255,"locked":true,"priority":1,"focus":3},{"x":-24,"y":28.5,"zoomX":100,"zoomY":100,"visible":true,"target":2,"graphicFrame":2,"opacity":110,"priority":1,"focus":3},{"x":-8,"y":21.5,"zoomX":100,"zoomY":100,"visible":true,"target":2,"graphicFrame":2,"opacity":180,"priority":1,"focus":3},{"x":32,"y":32,"zoomX":100,"zoomY":100,"visible":true,"target":2,"graphicFrame":2,"opacity":110,"priority":1,"focus":3},{"x":-16,"y":16.5,"zoomX":100,"zoomY":100,"visible":true,"target":2,"graphicFrame":2,"opacity":180,"priority":1,"focus":3},{"x":28,"y":16.5,"zoomX":100,"zoomY":100,"visible":true,"target":2,"graphicFrame":2,"opacity":180,"priority":1,"focus":3},{"x":16,"y":14,"zoomX":100,"zoomY":100,"visible":true,"target":2,"graphicFrame":2,"opacity":180,"priority":1,"focus":3},{"x":8,"y":29.5,"zoomX":100,"zoomY":100,"visible":true,"target":2,"graphicFrame":2,"opacity":110,"priority":1,"focus":3}],[{"x":0,"y":0,"zoomX":100,"zoomY":100,"visible":true,"target":0,"graphicFrame":0,"opacity":255,"locked":true,"priority":1,"focus":3},{"x":128,"y":-64,"zoomX":100,"zoomY":100,"visible":true,"target":1,"graphicFrame":0,"opacity":255,"locked":true,"priority":1,"focus":3},{"x":-24,"y":32.5,"zoomX":100,"zoomY":100,"visible":true,"target":2,"graphicFrame":2,"opacity":60,"priority":1,"focus":3},{"x":-8,"y":25.5,"zoomX":100,"zoomY":100,"visible":true,"target":2,"graphicFrame":2,"opacity":110,"priority":1,"focus":3},{"x":32,"y":36,"zoomX":100,"zoomY":100,"visible":true,"target":2,"graphicFrame":2,"opacity":60,"priority":1,"focus":3},{"x":-16,"y":20.5,"zoomX":100,"zoomY":100,"visible":true,"target":2,"graphicFrame":2,"opacity":180,"priority":1,"focus":3},{"x":28,"y":20.5,"zoomX":100,"zoomY":100,"visible":true,"target":2,"graphicFrame":2,"opacity":180,"priority":1,"focus":3},{"x":16,"y":18,"zoomX":100,"zoomY":100,"visible":true,"target":2,"graphicFrame":2,"opacity":180,"priority":1,"focus":3},{"x":8,"y":33.5,"zoomX":100,"zoomY":100,"visible":true,"target":2,"graphicFrame":2,"opacity":60,"priority":1,"focus":3}],[{"x":0,"y":0,"zoomX":100,"zoomY":100,"visible":true,"target":0,"graphicFrame":0,"opacity":255,"locked":true,"priority":1,"focus":3},{"x":128,"y":-64,"zoomX":100,"zoomY":100,"visible":true,"target":1,"graphicFrame":0,"opacity":255,"locked":true,"priority":1,"focus":3},{"x":-8,"y":29.5,"zoomX":100,"zoomY":100,"visible":true,"target":2,"graphicFrame":2,"opacity":60,"priority":1,"focus":3},{"x":-16,"y":24.5,"zoomX":100,"zoomY":100,"visible":true,"target":2,"graphicFrame":2,"opacity":110,"priority":1,"focus":3},{"x":28,"y":24.5,"zoomX":100,"zoomY":100,"visible":true,"target":2,"graphicFrame":2,"opacity":110,"priority":1,"focus":3},{"x":16,"y":22,"zoomX":100,"zoomY":100,"visible":true,"target":2,"graphicFrame":2,"opacity":180,"priority":1,"focus":3}],[{"x":0,"y":0,"zoomX":100,"zoomY":100,"visible":true,"target":0,"graphicFrame":0,"opacity":255,"locked":true,"priority":1,"focus":3},{"x":128,"y":-64,"zoomX":100,"zoomY":100,"visible":true,"target":1,"graphicFrame":0,"opacity":255,"locked":true,"priority":1,"focus":3},{"x":-16,"y":28.5,"zoomX":100,"zoomY":100,"visible":true,"target":2,"graphicFrame":2,"opacity":60,"priority":1,"focus":3},{"x":28,"y":28.5,"zoomX":100,"zoomY":100,"visible":true,"target":2,"graphicFrame":2,"opacity":60,"priority":1,"focus":3},{"x":16,"y":26,"zoomX":100,"zoomY":100,"visible":true,"target":2,"graphicFrame":2,"opacity":110,"priority":1,"focus":3}],[{"x":0,"y":0,"zoomX":100,"zoomY":100,"visible":true,"target":0,"graphicFrame":0,"opacity":255,"locked":true,"priority":1,"focus":3},{"x":128,"y":-64,"zoomX":100,"zoomY":100,"visible":true,"target":1,"graphicFrame":0,"opacity":255,"locked":true,"priority":1,"focus":3},{"x":16,"y":30,"zoomX":100,"zoomY":100,"visible":true,"target":2,"graphicFrame":2,"opacity":60,"priority":1,"focus":3}],[{"x":0,"y":0,"zoomX":100,"zoomY":100,"visible":true,"target":0,"graphicFrame":0,"opacity":255,"locked":true,"priority":1,"focus":3},{"x":128,"y":-64,"zoomX":100,"zoomY":100,"visible":true,"target":1,"graphicFrame":0,"opacity":255,"locked":true,"priority":1,"focus":3}]],"frameTimedEvents":{"0":[{"frameIndex":0,"resourceName":"PRSFX- Acid Spray.wav","volume":100,"pitch":100,"eventType":"AnimTimedSoundEvent"}]},"position":1,"hue":0}]