{
	"0": {
		"52524a": "15321e",
		"6a6a6a": "224228",
		"5a5a62": "4b382a",
		"acacac": "69ad6c",
		"838394": "a48d76",
		"fefefe": "fff2e5",
		"8b8b8b": "3e6244",
		"cdcdcd": "cbc4a2",
		"a4a4ac": "bca88c",
		"6abdff": "ff78fa"
	},
	"1": {
		"52524a": "47121b",
		"6a6a6a": "6e1e26",
		"5a5a62": "2b265d",
		"acacac": "d4857c",
		"838394": "3d3c8c",
		"fefefe": "cdd9fa",
		"8b8b8b": "8b312e",
		"cdcdcd": "91a1e3",
		"a4a4ac": "686dc0",
		"6abdff": "ffcf47",
		"9c3141": "bc2d51",
		"de5252": "de5291"
	},
	"2": {
		"52524a": "0e213a",
		"6a6a6a": "1d365e",
		"5a5a62": "722f15",
		"acacac": "7d95bf",
		"838394": "833d19",
		"fefefe": "ffcc7d",
		"8b8b8b": "385594",
		"cdcdcd": "d48e3c",
		"a4a4ac": "a45f34",
		"6abdff": "2aebcf"
	}
}