{
	"textures": [
		{
			"image": "678.png",
			"format": "RGBA8888",
			"size": {
				"w": 55,
				"h": 55
			},
			"scale": 0.333,
			"frames": [
				{
					"filename": "0001.png",
					"rotated": false,
					"trimmed": false,
					"sourceSize": {
						"w": 96,
						"h": 96
					},
					"spriteSourceSize": {
						"x": 25,
						"y": 20,
						"w": 46,
						"h": 55
					},
					"frame": {
						"x": 0,
						"y": 0,
						"w": 46,
						"h": 55
					}
				}
			]
		}
	],
	"meta": {
		"app": "https://www.codeandweb.com/texturepacker",
		"version": "3.0",
		"smartupdate": "$TexturePacker:SmartUpdate:7b46b2656390e5ddac94370837e7cdaa:7f76286d5acb65066eff0c2532fa7fea:887aa14e4a3a3e9141c6ae460f968db1$"
	}
}
