{
	"textures": [
		{
			"image": "359-mega.png",
			"format": "RGBA8888",
			"size": {
				"w": 70,
				"h": 70
			},
			"scale": 1,
			"frames": [
				{
					"filename": "0001.png",
					"rotated": false,
					"trimmed": false,
					"sourceSize": {
						"w": 68,
						"h": 70
					},
					"spriteSourceSize": {
						"x": 0,
						"y": 0,
						"w": 68,
						"h": 70
					},
					"frame": {
						"x": 0,
						"y": 0,
						"w": 68,
						"h": 70
					}
				}
			]
		}
	],
	"meta": {
		"app": "https://www.codeandweb.com/texturepacker",
		"version": "3.0",
		"smartupdate": "$TexturePacker:SmartUpdate:a4a0f7f26dfbf9c0090bf05d6a3dc1ce:37054e6e0cad7c8c5a06d77755ef1f1d:597de57b9b54edf6a4cc7dadf7a61ea6$"
	}
}
