{ "frames": [
   {
    "filename": "0001.png",
    "frame": { "x": 116, "y": 124, "w": 40, "h": 59 },
    "rotated": false,
    "trimmed": true,
    "spriteSourceSize": { "x": 0, "y": 4, "w": 40, "h": 59 },
    "sourceSize": { "w": 43, "h": 63 },
    "duration": 100
   },
   {
    "filename": "0002.png",
    "frame": { "x": 40, "y": 185, "w": 40, "h": 58 },
    "rotated": false,
    "trimmed": true,
    "spriteSourceSize": { "x": 0, "y": 5, "w": 40, "h": 58 },
    "sourceSize": { "w": 43, "h": 63 },
    "duration": 100
   },
   {
    "filename": "0003.png",
    "frame": { "x": 77, "y": 298, "w": 40, "h": 56 },
    "rotated": false,
    "trimmed": true,
    "spriteSourceSize": { "x": 0, "y": 7, "w": 40, "h": 56 },
    "sourceSize": { "w": 43, "h": 63 },
    "duration": 100
   },
   {
    "filename": "0004.png",
    "frame": { "x": 162, "y": 299, "w": 40, "h": 56 },
    "rotated": false,
    "trimmed": true,
    "spriteSourceSize": { "x": 0, "y": 7, "w": 40, "h": 56 },
    "sourceSize": { "w": 43, "h": 63 },
    "duration": 100
   },
   {
    "filename": "0005.png",
    "frame": { "x": 202, "y": 299, "w": 41, "h": 54 },
    "rotated": false,
    "trimmed": true,
    "spriteSourceSize": { "x": 0, "y": 9, "w": 41, "h": 54 },
    "sourceSize": { "w": 43, "h": 63 },
    "duration": 100
   },
   {
    "filename": "0006.png",
    "frame": { "x": 117, "y": 300, "w": 41, "h": 54 },
    "rotated": false,
    "trimmed": true,
    "spriteSourceSize": { "x": 1, "y": 9, "w": 41, "h": 54 },
    "sourceSize": { "w": 43, "h": 63 },
    "duration": 100
   },
   {
    "filename": "0007.png",
    "frame": { "x": 121, "y": 245, "w": 41, "h": 55 },
    "rotated": false,
    "trimmed": true,
    "spriteSourceSize": { "x": 1, "y": 8, "w": 41, "h": 55 },
    "sourceSize": { "w": 43, "h": 63 },
    "duration": 100
   },
   {
    "filename": "0008.png",
    "frame": { "x": 80, "y": 242, "w": 41, "h": 56 },
    "rotated": false,
    "trimmed": true,
    "spriteSourceSize": { "x": 1, "y": 7, "w": 41, "h": 56 },
    "sourceSize": { "w": 43, "h": 63 },
    "duration": 100
   },
   {
    "filename": "0009.png",
    "frame": { "x": 0, "y": 244, "w": 40, "h": 57 },
    "rotated": false,
    "trimmed": true,
    "spriteSourceSize": { "x": 3, "y": 6, "w": 40, "h": 57 },
    "sourceSize": { "w": 43, "h": 63 },
    "duration": 100
   },
   {
    "filename": "0010.png",
    "frame": { "x": 194, "y": 240, "w": 39, "h": 59 },
    "rotated": false,
    "trimmed": true,
    "spriteSourceSize": { "x": 3, "y": 4, "w": 39, "h": 59 },
    "sourceSize": { "w": 43, "h": 63 },
    "duration": 100
   },
   {
    "filename": "0011.png",
    "frame": { "x": 0, "y": 125, "w": 37, "h": 59 },
    "rotated": false,
    "trimmed": true,
    "spriteSourceSize": { "x": 3, "y": 4, "w": 37, "h": 59 },
    "sourceSize": { "w": 43, "h": 63 },
    "duration": 100
   },
   {
    "filename": "0012.png",
    "frame": { "x": 156, "y": 184, "w": 38, "h": 61 },
    "rotated": false,
    "trimmed": true,
    "spriteSourceSize": { "x": 2, "y": 2, "w": 38, "h": 61 },
    "sourceSize": { "w": 43, "h": 63 },
    "duration": 100
   },
   {
    "filename": "0013.png",
    "frame": { "x": 40, "y": 243, "w": 37, "h": 62 },
    "rotated": false,
    "trimmed": true,
    "spriteSourceSize": { "x": 2, "y": 1, "w": 37, "h": 62 },
    "sourceSize": { "w": 43, "h": 63 },
    "duration": 100
   },
   {
    "filename": "0014.png",
    "frame": { "x": 158, "y": 0, "w": 39, "h": 62 },
    "rotated": false,
    "trimmed": true,
    "spriteSourceSize": { "x": 1, "y": 1, "w": 39, "h": 62 },
    "sourceSize": { "w": 43, "h": 63 },
    "duration": 100
   },
   {
    "filename": "0015.png",
    "frame": { "x": 156, "y": 62, "w": 39, "h": 61 },
    "rotated": false,
    "trimmed": true,
    "spriteSourceSize": { "x": 1, "y": 2, "w": 39, "h": 61 },
    "sourceSize": { "w": 43, "h": 63 },
    "duration": 100
   },
   {
    "filename": "0016.png",
    "frame": { "x": 197, "y": 0, "w": 40, "h": 60 },
    "rotated": false,
    "trimmed": true,
    "spriteSourceSize": { "x": 0, "y": 3, "w": 40, "h": 60 },
    "sourceSize": { "w": 43, "h": 63 },
    "duration": 100
   },
   {
    "filename": "0017.png",
    "frame": { "x": 116, "y": 124, "w": 40, "h": 59 },
    "rotated": false,
    "trimmed": true,
    "spriteSourceSize": { "x": 0, "y": 4, "w": 40, "h": 59 },
    "sourceSize": { "w": 43, "h": 63 },
    "duration": 100
   },
   {
    "filename": "0018.png",
    "frame": { "x": 40, "y": 185, "w": 40, "h": 58 },
    "rotated": false,
    "trimmed": true,
    "spriteSourceSize": { "x": 0, "y": 5, "w": 40, "h": 58 },
    "sourceSize": { "w": 43, "h": 63 },
    "duration": 100
   },
   {
    "filename": "0019.png",
    "frame": { "x": 77, "y": 298, "w": 40, "h": 56 },
    "rotated": false,
    "trimmed": true,
    "spriteSourceSize": { "x": 0, "y": 7, "w": 40, "h": 56 },
    "sourceSize": { "w": 43, "h": 63 },
    "duration": 100
   },
   {
    "filename": "0020.png",
    "frame": { "x": 162, "y": 299, "w": 40, "h": 56 },
    "rotated": false,
    "trimmed": true,
    "spriteSourceSize": { "x": 0, "y": 7, "w": 40, "h": 56 },
    "sourceSize": { "w": 43, "h": 63 },
    "duration": 100
   },
   {
    "filename": "0021.png",
    "frame": { "x": 202, "y": 299, "w": 41, "h": 54 },
    "rotated": false,
    "trimmed": true,
    "spriteSourceSize": { "x": 0, "y": 9, "w": 41, "h": 54 },
    "sourceSize": { "w": 43, "h": 63 },
    "duration": 100
   },
   {
    "filename": "0022.png",
    "frame": { "x": 117, "y": 300, "w": 41, "h": 54 },
    "rotated": false,
    "trimmed": true,
    "spriteSourceSize": { "x": 1, "y": 9, "w": 41, "h": 54 },
    "sourceSize": { "w": 43, "h": 63 },
    "duration": 100
   },
   {
    "filename": "0023.png",
    "frame": { "x": 121, "y": 245, "w": 41, "h": 55 },
    "rotated": false,
    "trimmed": true,
    "spriteSourceSize": { "x": 1, "y": 8, "w": 41, "h": 55 },
    "sourceSize": { "w": 43, "h": 63 },
    "duration": 100
   },
   {
    "filename": "0024.png",
    "frame": { "x": 80, "y": 242, "w": 41, "h": 56 },
    "rotated": false,
    "trimmed": true,
    "spriteSourceSize": { "x": 1, "y": 7, "w": 41, "h": 56 },
    "sourceSize": { "w": 43, "h": 63 },
    "duration": 100
   },
   {
    "filename": "0025.png",
    "frame": { "x": 0, "y": 244, "w": 40, "h": 57 },
    "rotated": false,
    "trimmed": true,
    "spriteSourceSize": { "x": 3, "y": 6, "w": 40, "h": 57 },
    "sourceSize": { "w": 43, "h": 63 },
    "duration": 100
   },
   {
    "filename": "0026.png",
    "frame": { "x": 194, "y": 240, "w": 39, "h": 59 },
    "rotated": false,
    "trimmed": true,
    "spriteSourceSize": { "x": 3, "y": 4, "w": 39, "h": 59 },
    "sourceSize": { "w": 43, "h": 63 },
    "duration": 100
   },
   {
    "filename": "0027.png",
    "frame": { "x": 0, "y": 125, "w": 37, "h": 59 },
    "rotated": false,
    "trimmed": true,
    "spriteSourceSize": { "x": 3, "y": 4, "w": 37, "h": 59 },
    "sourceSize": { "w": 43, "h": 63 },
    "duration": 100
   },
   {
    "filename": "0028.png",
    "frame": { "x": 156, "y": 184, "w": 38, "h": 61 },
    "rotated": false,
    "trimmed": true,
    "spriteSourceSize": { "x": 2, "y": 2, "w": 38, "h": 61 },
    "sourceSize": { "w": 43, "h": 63 },
    "duration": 100
   },
   {
    "filename": "0029.png",
    "frame": { "x": 40, "y": 243, "w": 37, "h": 62 },
    "rotated": false,
    "trimmed": true,
    "spriteSourceSize": { "x": 2, "y": 1, "w": 37, "h": 62 },
    "sourceSize": { "w": 43, "h": 63 },
    "duration": 100
   },
   {
    "filename": "0030.png",
    "frame": { "x": 158, "y": 0, "w": 39, "h": 62 },
    "rotated": false,
    "trimmed": true,
    "spriteSourceSize": { "x": 1, "y": 1, "w": 39, "h": 62 },
    "sourceSize": { "w": 43, "h": 63 },
    "duration": 100
   },
   {
    "filename": "0031.png",
    "frame": { "x": 156, "y": 62, "w": 39, "h": 61 },
    "rotated": false,
    "trimmed": true,
    "spriteSourceSize": { "x": 1, "y": 2, "w": 39, "h": 61 },
    "sourceSize": { "w": 43, "h": 63 },
    "duration": 100
   },
   {
    "filename": "0032.png",
    "frame": { "x": 197, "y": 0, "w": 40, "h": 60 },
    "rotated": false,
    "trimmed": true,
    "spriteSourceSize": { "x": 0, "y": 3, "w": 40, "h": 60 },
    "sourceSize": { "w": 43, "h": 63 },
    "duration": 100
   },
   {
    "filename": "0033.png",
    "frame": { "x": 116, "y": 124, "w": 40, "h": 59 },
    "rotated": false,
    "trimmed": true,
    "spriteSourceSize": { "x": 0, "y": 4, "w": 40, "h": 59 },
    "sourceSize": { "w": 43, "h": 63 },
    "duration": 100
   },
   {
    "filename": "0034.png",
    "frame": { "x": 40, "y": 185, "w": 40, "h": 58 },
    "rotated": false,
    "trimmed": true,
    "spriteSourceSize": { "x": 0, "y": 5, "w": 40, "h": 58 },
    "sourceSize": { "w": 43, "h": 63 },
    "duration": 100
   },
   {
    "filename": "0035.png",
    "frame": { "x": 77, "y": 298, "w": 40, "h": 56 },
    "rotated": false,
    "trimmed": true,
    "spriteSourceSize": { "x": 0, "y": 7, "w": 40, "h": 56 },
    "sourceSize": { "w": 43, "h": 63 },
    "duration": 100
   },
   {
    "filename": "0036.png",
    "frame": { "x": 162, "y": 299, "w": 40, "h": 56 },
    "rotated": false,
    "trimmed": true,
    "spriteSourceSize": { "x": 0, "y": 7, "w": 40, "h": 56 },
    "sourceSize": { "w": 43, "h": 63 },
    "duration": 100
   },
   {
    "filename": "0037.png",
    "frame": { "x": 202, "y": 299, "w": 41, "h": 54 },
    "rotated": false,
    "trimmed": true,
    "spriteSourceSize": { "x": 0, "y": 9, "w": 41, "h": 54 },
    "sourceSize": { "w": 43, "h": 63 },
    "duration": 100
   },
   {
    "filename": "0038.png",
    "frame": { "x": 117, "y": 300, "w": 41, "h": 54 },
    "rotated": false,
    "trimmed": true,
    "spriteSourceSize": { "x": 1, "y": 9, "w": 41, "h": 54 },
    "sourceSize": { "w": 43, "h": 63 },
    "duration": 100
   },
   {
    "filename": "0039.png",
    "frame": { "x": 121, "y": 245, "w": 41, "h": 55 },
    "rotated": false,
    "trimmed": true,
    "spriteSourceSize": { "x": 1, "y": 8, "w": 41, "h": 55 },
    "sourceSize": { "w": 43, "h": 63 },
    "duration": 100
   },
   {
    "filename": "0040.png",
    "frame": { "x": 80, "y": 242, "w": 41, "h": 56 },
    "rotated": false,
    "trimmed": true,
    "spriteSourceSize": { "x": 1, "y": 7, "w": 41, "h": 56 },
    "sourceSize": { "w": 43, "h": 63 },
    "duration": 100
   },
   {
    "filename": "0041.png",
    "frame": { "x": 0, "y": 244, "w": 40, "h": 57 },
    "rotated": false,
    "trimmed": true,
    "spriteSourceSize": { "x": 3, "y": 6, "w": 40, "h": 57 },
    "sourceSize": { "w": 43, "h": 63 },
    "duration": 100
   },
   {
    "filename": "0042.png",
    "frame": { "x": 194, "y": 240, "w": 39, "h": 59 },
    "rotated": false,
    "trimmed": true,
    "spriteSourceSize": { "x": 3, "y": 4, "w": 39, "h": 59 },
    "sourceSize": { "w": 43, "h": 63 },
    "duration": 100
   },
   {
    "filename": "0043.png",
    "frame": { "x": 0, "y": 125, "w": 37, "h": 59 },
    "rotated": false,
    "trimmed": true,
    "spriteSourceSize": { "x": 3, "y": 4, "w": 37, "h": 59 },
    "sourceSize": { "w": 43, "h": 63 },
    "duration": 100
   },
   {
    "filename": "0044.png",
    "frame": { "x": 156, "y": 184, "w": 38, "h": 61 },
    "rotated": false,
    "trimmed": true,
    "spriteSourceSize": { "x": 2, "y": 2, "w": 38, "h": 61 },
    "sourceSize": { "w": 43, "h": 63 },
    "duration": 100
   },
   {
    "filename": "0045.png",
    "frame": { "x": 40, "y": 243, "w": 37, "h": 62 },
    "rotated": false,
    "trimmed": true,
    "spriteSourceSize": { "x": 2, "y": 1, "w": 37, "h": 62 },
    "sourceSize": { "w": 43, "h": 63 },
    "duration": 100
   },
   {
    "filename": "0046.png",
    "frame": { "x": 158, "y": 0, "w": 39, "h": 62 },
    "rotated": false,
    "trimmed": true,
    "spriteSourceSize": { "x": 1, "y": 1, "w": 39, "h": 62 },
    "sourceSize": { "w": 43, "h": 63 },
    "duration": 100
   },
   {
    "filename": "0047.png",
    "frame": { "x": 156, "y": 62, "w": 39, "h": 61 },
    "rotated": false,
    "trimmed": true,
    "spriteSourceSize": { "x": 1, "y": 2, "w": 39, "h": 61 },
    "sourceSize": { "w": 43, "h": 63 },
    "duration": 100
   },
   {
    "filename": "0048.png",
    "frame": { "x": 197, "y": 0, "w": 40, "h": 60 },
    "rotated": false,
    "trimmed": true,
    "spriteSourceSize": { "x": 0, "y": 3, "w": 40, "h": 60 },
    "sourceSize": { "w": 43, "h": 63 },
    "duration": 100
   },
   {
    "filename": "0049.png",
    "frame": { "x": 116, "y": 124, "w": 40, "h": 59 },
    "rotated": false,
    "trimmed": true,
    "spriteSourceSize": { "x": 0, "y": 4, "w": 40, "h": 59 },
    "sourceSize": { "w": 43, "h": 63 },
    "duration": 100
   },
   {
    "filename": "0050.png",
    "frame": { "x": 195, "y": 181, "w": 40, "h": 59 },
    "rotated": false,
    "trimmed": true,
    "spriteSourceSize": { "x": 0, "y": 4, "w": 40, "h": 59 },
    "sourceSize": { "w": 43, "h": 63 },
    "duration": 100
   },
   {
    "filename": "0051.png",
    "frame": { "x": 118, "y": 0, "w": 40, "h": 61 },
    "rotated": false,
    "trimmed": true,
    "spriteSourceSize": { "x": 1, "y": 2, "w": 40, "h": 61 },
    "sourceSize": { "w": 43, "h": 63 },
    "duration": 100
   },
   {
    "filename": "0052.png",
    "frame": { "x": 0, "y": 0, "w": 40, "h": 62 },
    "rotated": false,
    "trimmed": true,
    "spriteSourceSize": { "x": 1, "y": 1, "w": 40, "h": 62 },
    "sourceSize": { "w": 43, "h": 63 },
    "duration": 100
   },
   {
    "filename": "0053.png",
    "frame": { "x": 118, "y": 61, "w": 38, "h": 63 },
    "rotated": false,
    "trimmed": true,
    "spriteSourceSize": { "x": 2, "y": 0, "w": 38, "h": 63 },
    "sourceSize": { "w": 43, "h": 63 },
    "duration": 100
   },
   {
    "filename": "0054.png",
    "frame": { "x": 0, "y": 62, "w": 38, "h": 63 },
    "rotated": false,
    "trimmed": true,
    "spriteSourceSize": { "x": 2, "y": 0, "w": 38, "h": 63 },
    "sourceSize": { "w": 43, "h": 63 },
    "duration": 100
   },
   {
    "filename": "0055.png",
    "frame": { "x": 40, "y": 0, "w": 39, "h": 63 },
    "rotated": false,
    "trimmed": true,
    "spriteSourceSize": { "x": 1, "y": 0, "w": 39, "h": 63 },
    "sourceSize": { "w": 43, "h": 63 },
    "duration": 100
   },
   {
    "filename": "0056.png",
    "frame": { "x": 79, "y": 0, "w": 39, "h": 63 },
    "rotated": false,
    "trimmed": true,
    "spriteSourceSize": { "x": 1, "y": 0, "w": 39, "h": 63 },
    "sourceSize": { "w": 43, "h": 63 },
    "duration": 100
   },
   {
    "filename": "0057.png",
    "frame": { "x": 38, "y": 63, "w": 39, "h": 61 },
    "rotated": false,
    "trimmed": true,
    "spriteSourceSize": { "x": 1, "y": 2, "w": 39, "h": 61 },
    "sourceSize": { "w": 43, "h": 63 },
    "duration": 100
   },
   {
    "filename": "0058.png",
    "frame": { "x": 77, "y": 63, "w": 39, "h": 61 },
    "rotated": false,
    "trimmed": true,
    "spriteSourceSize": { "x": 1, "y": 2, "w": 39, "h": 61 },
    "sourceSize": { "w": 43, "h": 63 },
    "duration": 100
   },
   {
    "filename": "0059.png",
    "frame": { "x": 195, "y": 120, "w": 39, "h": 61 },
    "rotated": false,
    "trimmed": true,
    "spriteSourceSize": { "x": 1, "y": 2, "w": 39, "h": 61 },
    "sourceSize": { "w": 43, "h": 63 },
    "duration": 100
   },
   {
    "filename": "0060.png",
    "frame": { "x": 156, "y": 123, "w": 39, "h": 61 },
    "rotated": false,
    "trimmed": true,
    "spriteSourceSize": { "x": 1, "y": 2, "w": 39, "h": 61 },
    "sourceSize": { "w": 43, "h": 63 },
    "duration": 100
   },
   {
    "filename": "0061.png",
    "frame": { "x": 38, "y": 124, "w": 39, "h": 61 },
    "rotated": false,
    "trimmed": true,
    "spriteSourceSize": { "x": 1, "y": 2, "w": 39, "h": 61 },
    "sourceSize": { "w": 43, "h": 63 },
    "duration": 100
   },
   {
    "filename": "0062.png",
    "frame": { "x": 77, "y": 124, "w": 39, "h": 61 },
    "rotated": false,
    "trimmed": true,
    "spriteSourceSize": { "x": 1, "y": 2, "w": 39, "h": 61 },
    "sourceSize": { "w": 43, "h": 63 },
    "duration": 100
   },
   {
    "filename": "0063.png",
    "frame": { "x": 197, "y": 60, "w": 40, "h": 60 },
    "rotated": false,
    "trimmed": true,
    "spriteSourceSize": { "x": 0, "y": 3, "w": 40, "h": 60 },
    "sourceSize": { "w": 43, "h": 63 },
    "duration": 100
   },
   {
    "filename": "0064.png",
    "frame": { "x": 116, "y": 183, "w": 40, "h": 59 },
    "rotated": false,
    "trimmed": true,
    "spriteSourceSize": { "x": 0, "y": 4, "w": 40, "h": 59 },
    "sourceSize": { "w": 43, "h": 63 },
    "duration": 100
   },
   {
    "filename": "0065.png",
    "frame": { "x": 0, "y": 185, "w": 40, "h": 59 },
    "rotated": false,
    "trimmed": true,
    "spriteSourceSize": { "x": 0, "y": 4, "w": 40, "h": 59 },
    "sourceSize": { "w": 43, "h": 63 },
    "duration": 100
   }
 ],
 "meta": {
  "app": "https://www.aseprite.org/",
  "version": "1.3.12-x64",
  "image": "705.png",
  "format": "I8",
  "size": { "w": 243, "h": 355 },
  "scale": "1"
 }
}
